mcpi2/__init__.py
mcpi2/config/config.yaml
mcpi2/constants/__init__.py
mcpi2/f/__init__.py
mcpi2/f/image.py
mcpi2/logs/running_logs.log
mcpi2/utils/__init__.py
mcpi2/utils/common.py
mcpi2-0.0.2.dist-info/LICENSE.txt
mcpi2-0.0.2.dist-info/METADATA
mcpi2-0.0.2.dist-info/WHEEL
mcpi2-0.0.2.dist-info/dependency_links.txt
mcpi2-0.0.2.dist-info/top_level.txt
mcpi2-0.0.2.dist-info/RECORD
