Metadata-Version: 2.1
Name: mcpi2
Version: 0.0.2
Summary: Special tools for Minecraft
Home-page: https://github.com/GitHub-User228/mcpi2
Author: GitHub-User228
Author-email: egor.udalov13@gmail.com
License: UNKNOWN
Platform: UNKNOWN
Classifier: Programming Language :: Python :: 3
Classifier: License :: OSI Approved :: MIT License
Classifier: Operating System :: OS Independent
Requires-Python: >=3.9
License-File: LICENSE.txt
Requires-Dist: PyYAML
Requires-Dist: mcpi
Requires-Dist: opencv-python
Requires-Dist: setuptools
Requires-Dist: tqdm
Requires-Dist: wheel
